Workbook

Sheet Laufende Kosten
A1: LocalAd – Laufende Kosten (monatlich)
A2: Stand: Mai 2026 | Alle Beträge in EUR | Nur manuell aktualisieren wenn sich Kosten ändern
A4: Dienst | B4: Beschreibung | C4: Abrechnungsmodell | D4: Kosten / Monat | E4: Status | F4: Notizen
A5: Railway | B5: Backend (Node.js/Express) + PostgreSQL-Datenbank | C5: Hobby-Plan, monatlich | D5: 5 | E5: ✅ Aktiv | F5: Inkl. Postgres; steigt bei >500 MB RAM oder viel Traffic
A6: Domain getlocalad.de | B6: Jahresdomäne beim Registrar | C6: Jährlich (~12 €/Jahr) | D6: 1 | E6: ✅ Aktiv | F6: Entspricht ca. 1 €/Monat
A7: Resend | B7: E-Mail-Versand (Willkommen, Abo, Kontakt) | C7: Free Tier (3.000/Monat) | D7: 0 | E7: ✅ Aktiv | F7: Reicht bis ca. 3.000 Nutzer; danach 20 $/Monat
A8: Stripe | B8: Zahlungsabwicklung | C8: Keine Grundgebühr | D8: 0 | E8: ✅ Aktiv | F8: Nur Transaktionsgebühren – siehe Sheet 'Variable Kosten'
A9: GitHub | B9: Code-Repository | C9: Free Tier | D9: 0 | E9: ✅ Aktiv | F9: Free Tier reicht für das Projekt
A10: Chrome Web Store | B10: Entwickler-Registrierung (einmalig) | C10: Einmalig 5 USD | D10: 0 | E10: ✅ Bezahlt | F10: Einmalige Gebühr, bereits bezahlt
A12: Monatliche Fixkosten gesamt | D12: =SUM(D5:D10) -> 6
A14: ⚠️ Potenzielle Zusatzkosten ab Skalierung: Resend Paid (20 $/Monat ab 3.000+ Mails) · Railway Pro (20 $/Monat ab hohem Traffic) · Epidemic Sound für Musik (15 €/Monat)

Sheet Variable Kosten
A1: LocalAd – Variable Kosten: Stripe-Transaktionsgebühren
A2: Stripe berechnet pro Transaktion: 1,4% + 0,25 € (EU-Karte) | 2,9% + 0,25 € (Non-EU) | Abgerechnet monatlich
A4: Annahmen
A5: Abo-Preis pro Nutzer | B5: 3 | C5: €/Monat
A6: Stripe-Gebühr EU (Prozent) | B6: 0.014 | C6: 1,4%
A7: Stripe-Gebühr EU (Fix) | B7: 0.25 | C7: € pro Transaktion
A8: Anteil EU-Karten | B8: 0.95 | C8: 95% angenommen
A10: Szenario | B10: Nutzer | C10: Umsatz / Monat | D10: Stripe-Gebühr / Monat | E10: Fixkosten / Monat | F10: Kosten gesamt | G10: Gewinn / Monat
A11: Aktuell (MVP) | B11: 0 | C11: =B11*$B$5 -> 0 | D11: =B11*($B$5*$B$6+$B$7)*$B$8 -> 0 | E11: ='Laufende Kosten'!D11 -> 0 | F11: =D11+E11 -> 0 | G11: =C11-F11 -> 0
A12: Frühe Tester | B12: 10 | C12: =B12*$B$5 -> 30 | D12: =B12*($B$5*$B$6+$B$7)*$B$8 -> 2.774 | E12: ='Laufende Kosten'!D11 -> 0 | F12: =D12+E12 -> 2.774 | G12: =C12-F12 -> 27.226
A13: Erste Welle | B13: 50 | C13: =B13*$B$5 -> 150 | D13: =B13*($B$5*$B$6+$B$7)*$B$8 -> 13.87 | E13: ='Laufende Kosten'!D11 -> 0 | F13: =D13+E13 -> 13.87 | G13: =C13-F13 -> 136.13
A14: Break-even | B14: 100 | C14: =B14*$B$5 -> 300 | D14: =B14*($B$5*$B$6+$B$7)*$B$8 -> 27.74 | E14: ='Laufende Kosten'!D11 -> 0 | F14: =D14+E14 -> 27.74 | G14: =C14-F14 -> 272.26
A15: Wachstumsphase | B15: 250 | C15: =B15*$B$5 -> 750 | D15: =B15*($B$5*$B$6+$B$7)*$B$8 -> 69.35 | E15: ='Laufende Kosten'!D11 -> 0 | F15: =D15+E15 -> 69.35 | G15: =C15-F15 -> 680.65
A16: Skalierung | B16: 500 | C16: =B16*$B$5 -> 1500 | D16: =B16*($B$5*$B$6+$B$7)*$B$8 -> 138.7 | E16: ='Laufende Kosten'!D11 -> 0 | F16: =D16+E16 -> 138.7 | G16: =C16-F16 -> 1361.3
A17: Ziel Jahr 1 | B17: 1000 | C17: =B17*$B$5 -> 3000 | D17: =B17*($B$5*$B$6+$B$7)*$B$8 -> 277.4 | E17: ='Laufende Kosten'!D11 -> 0 | F17: =D17+E17 -> 277.4 | G17: =C17-F17 -> 2722.6
